opyplus/__init__.py
opyplus/conf.py
opyplus/eio.py
opyplus/epm.py
opyplus/err.py
opyplus/exceptions.py
opyplus/mtd.py
opyplus/output_table.py
opyplus/summary_table.py
opyplus/util.py
opyplus/version.py
opyplus/compatibility/__init__.py
opyplus/compatibility/api.py
opyplus/compatibility/epw.py
opyplus/compatibility/simulation.py
opyplus/compatibility/util.py
opyplus/epgm/__init__.py
opyplus/epgm/api.py
opyplus/epgm/epgm.py
opyplus/epgm/external_file.py
opyplus/epgm/external_files_manager.py
opyplus/epgm/file_content.py
opyplus/epgm/link.py
opyplus/epgm/multi_table_queryset.py
opyplus/epgm/parse_idf.py
opyplus/epgm/queryset.py
opyplus/epgm/record.py
opyplus/epgm/record_hook.py
opyplus/epgm/relations_manager.py
opyplus/epgm/table.py
opyplus/epgm/util.py
opyplus/idd/__init__.py
opyplus/idd/api.py
opyplus/idd/field_descriptor.py
opyplus/idd/idd.py
opyplus/idd/idd_debug.py
opyplus/idd/table_descriptor.py
opyplus/idd/util.py
opyplus/idd/resources/V22-1-0-Energy+.idd
opyplus/idd/resources/V22-2-0-Energy+.idd
opyplus/idd/resources/V23-1-0-Energy+.idd
opyplus/idd/resources/V23-2-0-Energy+.idd
opyplus/idd/resources/V24-1-0-Energy+.idd
opyplus/idd/resources/V8-0-0-Energy+.idd
opyplus/idd/resources/V8-1-0-Energy+.idd
opyplus/idd/resources/V8-2-0-Energy+.idd
opyplus/idd/resources/V8-3-0-Energy+.idd
opyplus/idd/resources/V8-4-0-Energy+.idd
opyplus/idd/resources/V8-5-0-Energy+.idd
opyplus/idd/resources/V8-6-0-Energy+.idd
opyplus/idd/resources/V8-7-0-Energy+.idd
opyplus/idd/resources/V8-8-0-Energy+.idd
opyplus/idd/resources/V8-9-0-Energy+.idd
opyplus/idd/resources/V9-0-0-Energy+.idd
opyplus/idd/resources/V9-1-0-Energy+.idd
opyplus/idd/resources/V9-2-0-Energy+.idd
opyplus/idd/resources/V9-3-0-Energy+.idd
opyplus/idd/resources/V9-4-0-Energy+.idd
opyplus/idd/resources/V9-5-0-Energy+.idd
opyplus/idd/resources/V9-6-0-Energy+.idd
opyplus/idd/resources/__init__.py
opyplus/simulation/__init__.py
opyplus/simulation/api.py
opyplus/simulation/info.py
opyplus/simulation/resources.py
opyplus-2.0.7.dist-info/LICENSE.txt
opyplus-2.0.7.dist-info/METADATA
opyplus-2.0.7.dist-info/WHEEL
opyplus-2.0.7.dist-info/top_level.txt
opyplus-2.0.7.dist-info/RECORD
