Metadata-Version: 2.1
Name: opyplus
Version: 2.0.7
Summary: Python package to work with Energyplus input and output
Home-page: https://github.com/openergy/opyplus
Author: Openergy development team
Author-email: contact@openergy.fr
Classifier: Programming Language :: Python
Classifier: Development Status :: 5 - Production/Stable
Classifier: Intended Audience :: Science/Research
Classifier: Natural Language :: English
Classifier: Operating System :: POSIX :: Linux
Classifier: Programming Language :: Python :: 3.8
Classifier: Programming Language :: Python :: 3.9
Classifier: Programming Language :: Python :: 3.10
Classifier: Programming Language :: Python :: 3.11
Classifier: Programming Language :: Python :: 3.12
Classifier: Topic :: Scientific/Engineering :: Physics
License-File: LICENSE.txt
Requires-Dist: pandas <3.0.0,>=1.5.0
Requires-Dist: unidecode <2.0,>=1.0.22
Requires-Dist: python-slugify <6.0,>=3.0.2
Requires-Dist: charset-normalizer <4.0,>=3.2.0
